{
  "items": [
    {
      "tags": [
        "c",
        "arguments",
        "default-parameters"
      ],
      "owner": {
        "account_id": 18128,
        "reputation": 15895,
        "user_id": 41241,
        "user_type": "registered",
        "accept_rate": 79,
        "profile_image": "https://www.gravatar.com/avatar/10e7a4afa4bebca010d372055bcb694f?s=256&d=identicon&r=PG",
        "display_name": "Nathaniel Flath",
        "link": "https://stackoverflow.com/users/41241/nathaniel-flath"
      },
      "is_answered": true,
      "view_count": 318612,
      "protected_date": 1563533093,
      "accepted_answer_id": 1472151,
      "answer_count": 24,
      "score": 369,
      "last_activity_date": 1704790476,
      "creation_date": 1253803100,
      "last_edit_date": 1557306123,
      "question_id": 1472138,
      "content_license": "CC BY-SA 4.0",
      "link": "https://stackoverflow.com/questions/1472138/c-default-arguments",
      "title": "C default arguments"
    },
    {
      "tags": [
        "c#",
        "arrays",
        ".net",
        "linq"
      ],
      "owner": {
        "account_id": 4001,
        "reputation": 14977,
        "user_id": 5883,
        "user_type": "registered",
        "accept_rate": 100,
        "profile_image": "https://www.gravatar.com/avatar/5c761536d66f497e45ba8de2267b9ead?s=256&d=identicon&r=PG",
        "display_name": "hwiechers",
        "link": "https://stackoverflow.com/users/5883/hwiechers"
      },
      "is_answered": true,
      "view_count": 512015,
      "protected_date": 1604052822,
      "closed_date": 1729671273,
      "accepted_answer_id": 1547276,
      "answer_count": 23,
      "score": 369,
      "last_activity_date": 1704921701,
      "creation_date": 1255157905,
      "last_edit_date": 1665783725,
      "question_id": 1547252,
      "link": "https://stackoverflow.com/questions/1547252/how-do-i-concatenate-two-arrays-in-c",
      "closed_reason": "Duplicate",
      "title": "How do I concatenate two arrays in C#?"
    },
    {
      "tags": [
        "java",
        "methods",
        "garbage-collection",
        "call",
        "finalize"
      ],
      "owner": {
        "account_id": 44772,
        "reputation": 4765,
        "user_id": 131565,
        "user_type": "registered",
        "accept_rate": 55,
        "profile_image": "https://www.gravatar.com/avatar/8eb6d4d2a162b27954a1531b4937f64c?s=256&d=identicon&r=PG",
        "display_name": "Rajesh Kumar J",
        "link": "https://stackoverflow.com/users/131565/rajesh-kumar-j"
      },
      "is_answered": true,
      "view_count": 536682,
      "protected_date": 1474692019,
      "accepted_answer_id": 2506525,
      "answer_count": 18,
      "score": 369,
      "last_activity_date": 1649285009,
      "creation_date": 1269422659,
      "last_edit_date": 1542080525,
      "question_id": 2506488,
      "content_license": "CC BY-SA 4.0",
      "link": "https://stackoverflow.com/questions/2506488/when-is-the-finalize-method-called-in-java",
      "title": "When is the finalize() method called in Java?"
    },
    {
      "tags": [
        "java",
        "tuples"
      ],
      "owner": {
        "account_id": 116538,
        "reputation": 11182,
        "user_id": 305555,
        "user_type": "registered",
        "accept_rate": 53,
        "profile_image": "https://www.gravatar.com/avatar/8332794b2a951bc17586fb553447bf5c?s=256&d=identicon&r=PG",
        "display_name": "syker",
        "link": "https://stackoverflow.com/users/305555/syker"
      },
      "is_answered": true,
      "view_count": 786644,
      "closed_date": 1455984416,
      "accepted_answer_id": 2671052,
      "answer_count": 14,
      "score": 369,
      "last_activity_date": 1635501737,
      "creation_date": 1271712016,
      "last_edit_date": 1393610042,
      "question_id": 2670982,
      "link": "https://stackoverflow.com/questions/2670982/using-pairs-or-2-tuples-in-java",
      "closed_reason": "Duplicate",
      "title": "Using Pairs or 2-tuples in Java"
    },
    {
      "tags": [
        "android",
        "android-intent"
      ],
      "owner": {
        "account_id": 116912,
        "reputation": 4411,
        "user_id": 306410,
        "user_type": "registered",
        "accept_rate": 90,
        "profile_image": "https://www.gravatar.com/avatar/f25ca2674635e4abeec1025a2eb110e7?s=256&d=identicon&r=PG",
        "display_name": "2Real",
        "link": "https://stackoverflow.com/users/306410/2real"
      },
      "is_answered": true,
      "view_count": 489658,
      "protected_date": 1338615845,
      "accepted_answer_id": 2696617,
      "answer_count": 24,
      "score": 369,
      "last_activity_date": 1708600836,
      "creation_date": 1271988477,
      "last_edit_date": 1554447585,
      "question_id": 2695746,
      "content_license": "CC BY-SA 4.0",
      "link": "https://stackoverflow.com/questions/2695746/how-to-get-a-list-of-installed-android-applications-and-pick-one-to-run",
      "title": "How to get a list of installed android applications and pick one to run"
    },
    {
      "tags": [
        "java",
        "arrays",
        "string"
      ],
      "owner": {
        "account_id": 88036,
        "reputation": 207468,
        "user_id": 243782,
        "user_type": "registered",
        "accept_rate": 94,
        "profile_image": "https://i.sstatic.net/gInNr.png?s=256",
        "display_name": "Pentium10",
        "link": "https://stackoverflow.com/users/243782/pentium10"
      },
      "is_answered": true,
      "view_count": 1775006,
      "protected_date": 1436678772,
      "accepted_answer_id": 2843371,
      "answer_count": 20,
      "score": 369,
      "last_activity_date": 1680878004,
      "creation_date": 1274006250,
      "last_edit_date": 1678657137,
      "question_id": 2843366,
      "content_license": "CC BY-SA 4.0",
      "link": "https://stackoverflow.com/questions/2843366/how-to-add-new-elements-to-an-array",
      "title": "How to add new elements to an array?"
    },
    {
      "tags": [
        "java",
        "arrays",
        "backwards-compatibility",
        "variadic-functions"
      ],
      "owner": {
        "account_id": 143786,
        "reputation": 4044,
        "user_id": 352382,
        "user_type": "registered",
        "profile_image": "https://www.gravatar.com/avatar/3f2d20f61d0132f11d4511baa17061b1?s=256&d=identicon&r=PG",
        "display_name": "user362382",
        "link": "https://stackoverflow.com/users/352382/user362382"
      },
      "is_answered": true,
      "view_count": 314360,
      "accepted_answer_id": 2925300,
      "answer_count": 6,
      "score": 369,
      "last_activity_date": 1683218662,
      "creation_date": 1274996198,
      "last_edit_date": 1275036797,
      "question_id": 2925153,
      "content_license": "CC BY-SA 2.5",
      "link": "https://stackoverflow.com/questions/2925153/can-i-pass-an-array-as-arguments-to-a-method-with-variable-arguments-in-java",
      "title": "Can I pass an array as arguments to a method with variable arguments in Java?"
    },
    {
      "tags": [
        "php",
        "internationalization",
        "locale"
      ],
      "owner": {
        "account_id": 36067,
        "reputation": 28254,
        "user_id": 102635,
        "user_type": "registered",
        "accept_rate": 62,
        "profile_image": "https://www.gravatar.com/avatar/66764e3b08d2ece5d593de7b0799f0df?s=256&d=identicon&r=PG",
        "display_name": "Kirk Ouimet",
        "link": "https://stackoverflow.com/users/102635/kirk-ouimet"
      },
      "is_answered": true,
      "view_count": 595430,
      "protected_date": 1624738183,
      "accepted_answer_id": 3191729,
      "answer_count": 11,
      "score": 369,
      "last_activity_date": 1728542774,
      "creation_date": 1278472756,
      "last_edit_date": 1278473504,
      "question_id": 3191664,
      "content_license": "CC BY-SA 2.5",
      "link": "https://stackoverflow.com/questions/3191664/list-of-all-locales-and-their-short-codes",
      "title": "List of All Locales and Their Short Codes?"
    },
    {
      "tags": [
        "makefile"
      ],
      "owner": {
        "account_id": 5645,
        "reputation": 170199,
        "user_id": 9204,
        "user_type": "registered",
        "accept_rate": 82,
        "profile_image": "https://www.gravatar.com/avatar/c79937a093ff9e963c563e22cd385f30?s=256&d=identicon&r=PG",
        "display_name": "Alexey Romanov",
        "link": "https://stackoverflow.com/users/9204/alexey-romanov"
      },
      "is_answered": true,
      "view_count": 212557,
      "accepted_answer_id": 3931814,
      "answer_count": 4,
      "score": 369,
      "last_activity_date": 1723824859,
      "creation_date": 1287047951,
      "last_edit_date": 1671676941,
      "question_id": 3931741,
      "content_license": "CC BY-SA 4.0",
      "link": "https://stackoverflow.com/questions/3931741/why-does-make-think-the-target-is-up-to-date",
      "title": "Why does make think the target is up to date?"
    },
    {
      "tags": [
        "windows",
        "scheduled-tasks"
      ],
      "owner": {
        "account_id": 143663,
        "reputation": 10074,
        "user_id": 352157,
        "user_type": "registered",
        "accept_rate": 74,
        "profile_image": "https://www.gravatar.com/avatar/7a2b68ea3bfc81279c6c40a00930e098?s=256&d=identicon&r=PG",
        "display_name": "kacalapy",
        "link": "https://stackoverflow.com/users/352157/kacalapy"
      },
      "is_answered": true,
      "view_count": 688166,
      "closed_date": 1503505056,
      "accepted_answer_id": 4250516,
      "answer_count": 8,
      "score": 369,
      "last_activity_date": 1621961735,
      "creation_date": 1290455143,
      "last_edit_date": 1502384673,
      "question_id": 4249542,
      "link": "https://stackoverflow.com/questions/4249542/run-a-task-every-x-minutes-with-windows-task-scheduler",
      "closed_reason": "Not suitable for this site",
      "title": "Run a task every x-minutes with Windows Task Scheduler"
    },
    {
      "tags": [
        ".net",
        "asp.net-mvc-3",
        "difference",
        "viewbag",
        "viewdata"
      ],
      "owner": {
        "account_id": 215191,
        "reputation": 50931,
        "user_id": 469652,
        "user_type": "registered",
        "accept_rate": 89,
        "profile_image": "https://www.gravatar.com/avatar/551d9aed3cea734cf15e17fb20943901?s=256&d=identicon&r=PG",
        "display_name": "user469652",
        "link": "https://stackoverflow.com/users/469652/user469652"
      },
      "is_answered": true,
      "view_count": 242699,
      "accepted_answer_id": 4705446,
      "answer_count": 17,
      "score": 369,
      "last_activity_date": 1618235022,
      "creation_date": 1295182189,
      "last_edit_date": 1418427941,
      "question_id": 4705426,
      "content_license": "CC BY-SA 3.0",
      "link": "https://stackoverflow.com/questions/4705426/whats-the-difference-between-viewdata-and-viewbag",
      "title": "What&#39;s the difference between ViewData and ViewBag?"
    },
    {
      "tags": [
        "c#",
        ".net",
        "xsd"
      ],
      "owner": {
        "account_id": 67104,
        "reputation": 18395,
        "user_id": 196526,
        "user_type": "registered",
        "accept_rate": 95,
        "profile_image": "https://i.sstatic.net/0woAd.png?s=256",
        "display_name": "Bastien Vandamme",
        "link": "https://stackoverflow.com/users/196526/bastien-vandamme"
      },
      "is_answered": true,
      "view_count": 477206,
      "protected_date": 1394230760,
      "accepted_answer_id": 5217696,
      "answer_count": 11,
      "score": 369,
      "last_activity_date": 1611277632,
      "creation_date": 1299488286,
      "last_edit_date": 1426522348,
      "question_id": 5217665,
      "content_license": "CC BY-SA 3.0",
      "link": "https://stackoverflow.com/questions/5217665/how-to-generate-net-4-0-classes-from-xsd",
      "title": "How to generate .NET 4.0 classes from xsd?"
    },
    {
      "tags": [
        "java",
        "switch-statement",
        "instanceof"
      ],
      "owner": {
        "account_id": 180086,
        "reputation": 20594,
        "user_id": 413174,
        "user_type": "registered",
        "accept_rate": 87,
        "profile_image": "https://www.gravatar.com/avatar/f3adc2b3fc7f7b18b9608a4a5ab0ba24?s=256&d=identicon&r=PG",
        "display_name": "olidev",
        "link": "https://stackoverflow.com/users/413174/olidev"
      },
      "is_answered": true,
      "view_count": 441745,
      "protected_date": 1674125379,
      "accepted_answer_id": 5579385,
      "answer_count": 30,
      "score": 369,
      "last_activity_date": 1721203767,
      "creation_date": 1302170608,
      "last_edit_date": 1553700199,
      "question_id": 5579309,
      "content_license": "CC BY-SA 4.0",
      "link": "https://stackoverflow.com/questions/5579309/is-it-possible-to-use-the-instanceof-operator-in-a-switch-statement",
      "title": "Is it possible to use the instanceof operator in a switch statement?"
    },
    {
      "tags": [
        "java",
        "class",
        "classname"
      ],
      "owner": {
        "account_id": 87569,
        "reputation": 77468,
        "user_id": 242769,
        "user_type": "registered",
        "accept_rate": 91,
        "profile_image": "https://www.gravatar.com/avatar/8f1bfe0dcaa3cdc6633e8b80639e541a?s=256&d=identicon&r=PG",
        "display_name": "aryaxt",
        "link": "https://stackoverflow.com/users/242769/aryaxt"
      },
      "is_answered": true,
      "view_count": 809018,
      "accepted_answer_id": 6271460,
      "answer_count": 12,
      "score": 369,
      "last_activity_date": 1723706711,
      "creation_date": 1307479582,
      "last_edit_date": 1723706711,
      "question_id": 6271417,
      "content_license": "CC BY-SA 4.0",
      "link": "https://stackoverflow.com/questions/6271417/java-get-the-current-class-name",
      "title": "Java - get the current class name?"
    },
    {
      "tags": [
        "bash",
        "shell",
        "automation",
        "osx-snow-leopard"
      ],
      "owner": {
        "account_id": 359128,
        "reputation": 8593,
        "user_id": 700338,
        "user_type": "registered",
        "accept_rate": 85,
        "profile_image": "https://www.gravatar.com/avatar/7902263b74bcf3092872c2e869c1f1ad?s=256&d=identicon&r=PG",
        "display_name": "MZimmerman6",
        "link": "https://stackoverflow.com/users/700338/mzimmerman6"
      },
      "is_answered": true,
      "view_count": 367743,
      "closed_date": 1357119236,
      "accepted_answer_id": 6445525,
      "answer_count": 3,
      "score": 369,
      "last_activity_date": 1655940385,
      "creation_date": 1308756230,
      "last_edit_date": 1652387225,
      "question_id": 6442364,
      "link": "https://stackoverflow.com/questions/6442364/running-script-upon-login-in-mac-os-x",
      "closed_reason": "off topic",
      "title": "Running script upon login in mac OS X"
    },
    {
      "tags": [
        "objective-c",
        "nsstring",
        "warnings",
        "constants"
      ],
      "owner": {
        "account_id": 359320,
        "reputation": 32960,
        "user_id": 700663,
        "user_type": "registered",
        "accept_rate": 67,
        "profile_image": "https://www.gravatar.com/avatar/7c7672678c3e0413ccf50327d46dd4f0?s=256&d=identicon&r=PG",
        "display_name": "user4951",
        "link": "https://stackoverflow.com/users/700663/user4951"
      },
      "is_answered": true,
      "view_count": 63022,
      "accepted_answer_id": 6830983,
      "answer_count": 3,
      "score": 369,
      "last_activity_date": 1504119653,
      "creation_date": 1311677052,
      "last_edit_date": 1423001560,
      "question_id": 6828831,
      "content_license": "CC BY-SA 3.0",
      "link": "https://stackoverflow.com/questions/6828831/sending-const-nsstring-to-parameter-of-type-nsstring-discards-qualifier",
      "title": "&quot;sending &#39;const NSString *&#39; to parameter of type &#39;NSString *&#39; discards qualifiers&quot; warning"
    },
    {
      "tags": [
        "java",
        "variables",
        "properties",
        "system",
        "environment"
      ],
      "owner": {
        "account_id": 304573,
        "reputation": 33417,
        "user_id": 614157,
        "user_type": "registered",
        "accept_rate": 56,
        "profile_image": "https://i.sstatic.net/xGzdG.jpg?s=256",
        "display_name": "Praveen Sripati",
        "link": "https://stackoverflow.com/users/614157/praveen-sripati"
      },
      "is_answered": true,
      "view_count": 386501,
      "accepted_answer_id": 7055010,
      "answer_count": 2,
      "score": 369,
      "last_activity_date": 1604000304,
      "creation_date": 1313295490,
      "last_edit_date": 1325117911,
      "question_id": 7054972,
      "content_license": "CC BY-SA 3.0",
      "link": "https://stackoverflow.com/questions/7054972/java-system-properties-and-environment-variables",
      "title": "Java system properties and environment variables"
    },
    {
      "tags": [
        "css",
        "html",
        "scrollbar"
      ],
      "owner": {
        "account_id": 959937,
        "reputation": 4186,
        "user_id": 984523,
        "user_type": "registered",
        "accept_rate": 85,
        "profile_image": "https://i.sstatic.net/LVmkd.jpg?s=256",
        "display_name": "harisdev",
        "link": "https://stackoverflow.com/users/984523/harisdev"
      },
      "is_answered": true,
      "view_count": 639958,
      "protected_date": 1471960271,
      "accepted_answer_id": 14150577,
      "answer_count": 21,
      "score": 369,
      "last_activity_date": 1708380701,
      "creation_date": 1329070892,
      "last_edit_date": 1357937974,
      "question_id": 9251354,
      "content_license": "CC BY-SA 3.0",
      "link": "https://stackoverflow.com/questions/9251354/css-customized-scroll-bar-in-div",
      "title": "CSS customized scroll bar in div"
    },
    {
      "tags": [
        "python",
        "pip"
      ],
      "owner": {
        "account_id": 402278,
        "reputation": 4057,
        "user_id": 769349,
        "user_type": "registered",
        "accept_rate": 93,
        "profile_image": "https://www.gravatar.com/avatar/eb60820bd56d62356ee9bfc44358a663?s=256&d=identicon&r=PG",
        "display_name": "Florin",
        "link": "https://stackoverflow.com/users/769349/florin"
      },
      "is_answered": true,
      "view_count": 486413,
      "accepted_answer_id": 9956813,
      "answer_count": 9,
      "score": 369,
      "last_activity_date": 1690440087,
      "creation_date": 1333204186,
      "last_edit_date": 1333204283,
      "question_id": 9956741,
      "content_license": "CC BY-SA 3.0",
      "link": "https://stackoverflow.com/questions/9956741/how-to-install-multiple-python-packages-at-once-using-pip",
      "title": "How to install multiple python packages at once using pip "
    },
    {
      "tags": [
        "python",
        "function",
        "multiprocessing",
        "return-value",
        "python-multiprocessing"
      ],
      "owner": {
        "account_id": 1181955,
        "reputation": 21180,
        "user_id": 1156707,
        "user_type": "registered",
        "accept_rate": 91,
        "profile_image": "https://www.gravatar.com/avatar/99055b620fb3a9d30a8f6ac480c25227?s=256&d=identicon&r=PG",
        "display_name": "Louis Thibault",
        "link": "https://stackoverflow.com/users/1156707/louis-thibault"
      },
      "is_answered": true,
      "view_count": 430056,
      "accepted_answer_id": 10415215,
      "answer_count": 14,
      "score": 369,
      "last_activity_date": 1702651937,
      "creation_date": 1335966274,
      "last_edit_date": 1697852125,
      "question_id": 10415028,
      "content_license": "CC BY-SA 4.0",
      "link": "https://stackoverflow.com/questions/10415028/how-can-i-get-the-return-value-of-a-function-passed-to-multiprocessing-process",
      "title": "How can I get the return value of a function passed to multiprocessing.Process?"
    },
    {
      "tags": [
        "mysql"
      ],
      "owner": {
        "account_id": 159353,
        "reputation": 26661,
        "user_id": 378622,
        "user_type": "registered",
        "accept_rate": 84,
        "profile_image": "https://www.gravatar.com/avatar/dc643a4278351110aac11e097854161f?s=256&d=identicon&r=PG",
        "display_name": "Ben G",
        "link": "https://stackoverflow.com/users/378622/ben-g"
      },
      "is_answered": true,
      "view_count": 546125,
      "protected_date": 1454000205,
      "accepted_answer_id": 12792977,
      "answer_count": 25,
      "score": 369,
      "last_activity_date": 1708607904,
      "creation_date": 1336344373,
      "last_edit_date": 1336346243,
      "question_id": 10474922,
      "content_license": "CC BY-SA 3.0",
      "link": "https://stackoverflow.com/questions/10474922/error-2006-hy000-mysql-server-has-gone-away",
      "title": "ERROR 2006 (HY000): MySQL server has gone away"
    },
    {
      "tags": [
        "python",
        "numpy"
      ],
      "owner": {
        "account_id": 310362,
        "reputation": 19213,
        "user_id": 623300,
        "user_type": "registered",
        "accept_rate": 79,
        "profile_image": "https://www.gravatar.com/avatar/ec3ba9362a9c2a43811d360af34ac31a?s=256&d=identicon&r=PG",
        "display_name": "Shan",
        "link": "https://stackoverflow.com/users/623300/shan"
      },
      "is_answered": true,
      "view_count": 467456,
      "protected_date": 1562320315,
      "accepted_answer_id": 10873843,
      "answer_count": 4,
      "score": 369,
      "last_activity_date": 1659170354,
      "creation_date": 1338756388,
      "last_edit_date": 1659170280,
      "question_id": 10873824,
      "content_license": "CC BY-SA 4.0",
      "link": "https://stackoverflow.com/questions/10873824/convert-2d-float-array-to-2d-int-array-in-numpy",
      "title": "Convert 2D float array to 2D int array in NumPy"
    },
    {
      "tags": [
        "c#",
        "sql-server",
        "t-sql",
        "stored-procedures"
      ],
      "owner": {
        "account_id": 331738,
        "reputation": 8061,
        "user_id": 656606,
        "user_type": "registered",
        "accept_rate": 98,
        "profile_image": "https://www.gravatar.com/avatar/3e37c5dfa9b2421bca24a3141b63f81f?s=256&d=identicon&r=PG",
        "display_name": "Sergey",
        "link": "https://stackoverflow.com/users/656606/sergey"
      },
      "is_answered": true,
      "view_count": 574649,
      "accepted_answer_id": 11105413,
      "answer_count": 14,
      "score": 369,
      "last_activity_date": 1724609112,
      "creation_date": 1340113621,
      "last_edit_date": 1508425796,
      "question_id": 11102358,
      "content_license": "CC BY-SA 3.0",
      "link": "https://stackoverflow.com/questions/11102358/how-to-pass-an-array-into-a-sql-server-stored-procedure",
      "title": "How to pass an array into a SQL Server stored procedure"
    },
    {
      "tags": [
        "authentication",
        "oauth",
        "oauth-2.0"
      ],
      "owner": {
        "account_id": 111541,
        "reputation": 20488,
        "user_id": 294619,
        "user_type": "registered",
        "accept_rate": 73,
        "profile_image": "https://www.gravatar.com/avatar/6c40c224c46a88e397529ece475dd9c0?s=256&d=identicon&r=PG",
        "display_name": "Aron Woost",
        "link": "https://stackoverflow.com/users/294619/aron-woost"
      },
      "is_answered": true,
      "view_count": 90444,
      "accepted_answer_id": 13389335,
      "answer_count": 8,
      "score": 369,
      "last_activity_date": 1661626932,
      "creation_date": 1352928720,
      "last_edit_date": 1661626932,
      "question_id": 13387698,
      "content_license": "CC BY-SA 4.0",
      "link": "https://stackoverflow.com/questions/13387698/why-is-there-an-authorization-code-flow-in-oauth2-when-implicit-flow-works-s",
      "title": "Why is there an &quot;Authorization Code&quot; flow in OAuth2 when &quot;Implicit&quot; flow works so well?"
    },
    {
      "tags": [
        "python",
        "pandas"
      ],
      "owner": {
        "account_id": 2036328,
        "reputation": 15377,
        "user_id": 1818608,
        "user_type": "registered",
        "accept_rate": 44,
        "profile_image": "https://www.gravatar.com/avatar/2c7fd43d0ea66acaf6eadc8062693a50?s=256&d=identicon&r=PG",
        "display_name": "Gill Bates",
        "link": "https://stackoverflow.com/users/1818608/gill-bates"
      },
      "is_answered": true,
      "view_count": 959209,
      "accepted_answer_id": 15315507,
      "answer_count": 5,
      "score": 369,
      "last_activity_date": 1691164833,
      "creation_date": 1362860269,
      "last_edit_date": 1658453335,
      "question_id": 15315452,
      "content_license": "CC BY-SA 4.0",
      "link": "https://stackoverflow.com/questions/15315452/selecting-with-complex-criteria-from-pandas-dataframe",
      "title": "Selecting with complex criteria from pandas.DataFrame"
    },
    {
      "tags": [
        "angularjs",
        "forms",
        "form-submit",
        "keypress",
        "enter"
      ],
      "owner": {
        "account_id": 1237207,
        "reputation": 11033,
        "user_id": 1200555,
        "user_type": "registered",
        "accept_rate": 87,
        "profile_image": "https://www.gravatar.com/avatar/4f304d6d2f8ec35a565ca50e537f8bf6?s=256&d=identicon&r=PG",
        "display_name": "ali",
        "link": "https://stackoverflow.com/users/1200555/ali"
      },
      "is_answered": true,
      "view_count": 388651,
      "accepted_answer_id": 15418063,
      "answer_count": 13,
      "score": 369,
      "last_activity_date": 1670742368,
      "creation_date": 1363285018,
      "last_edit_date": 1629307096,
      "question_id": 15417125,
      "content_license": "CC BY-SA 4.0",
      "link": "https://stackoverflow.com/questions/15417125/submit-form-on-pressing-enter-with-angularjs",
      "title": "Submit form on pressing Enter with AngularJS"
    },
    {
      "tags": [
        "macos",
        "postgresql",
        "homebrew"
      ],
      "owner": {
        "account_id": 160649,
        "reputation": 6367,
        "user_id": 724561,
        "user_type": "registered",
        "accept_rate": 89,
        "profile_image": "https://www.gravatar.com/avatar/101c16321b71a279daca4e5c33256e21?s=256&d=identicon&r=PG",
        "display_name": "klaffenboeck",
        "link": "https://stackoverflow.com/users/724561/klaffenboeck"
      },
      "is_answered": true,
      "view_count": 217221,
      "accepted_answer_id": 53745770,
      "answer_count": 13,
      "score": 369,
      "last_activity_date": 1708674381,
      "creation_date": 1374623825,
      "last_edit_date": 1656473756,
      "question_id": 17822974,
      "content_license": "CC BY-SA 4.0",
      "link": "https://stackoverflow.com/questions/17822974/postgres-fatal-database-files-are-incompatible-with-server",
      "title": "Postgres - FATAL: database files are incompatible with server"
    },
    {
      "tags": [
        "android",
        "android-fragments"
      ],
      "owner": {
        "account_id": 151269,
        "reputation": 16343,
        "user_id": 365019,
        "user_type": "registered",
        "accept_rate": 47,
        "profile_image": "https://www.gravatar.com/avatar/e15d917e41379dab0ace2f0128fca4a7?s=256&d=identicon&r=PG",
        "display_name": "AndroidDev",
        "link": "https://stackoverflow.com/users/365019/androiddev"
      },
      "is_answered": true,
      "view_count": 221387,
      "accepted_answer_id": 18634392,
      "answer_count": 9,
      "score": 369,
      "last_activity_date": 1592011548,
      "creation_date": 1378377839,
      "last_edit_date": 1413101536,
      "question_id": 18634207,
      "content_license": "CC BY-SA 3.0",
      "link": "https://stackoverflow.com/questions/18634207/difference-between-add-replace-and-addtobackstack",
      "title": "Difference between add(), replace(), and addToBackStack()"
    },
    {
      "tags": [
        "git",
        "git-push",
        "git-remote"
      ],
      "owner": {
        "account_id": 352865,
        "reputation": 12008,
        "user_id": 690204,
        "user_type": "registered",
        "accept_rate": 70,
        "profile_image": "https://www.gravatar.com/avatar/92091e0d874221db9e1c8cc90c47e43e?s=256&d=identicon&r=PG",
        "display_name": "alonisser",
        "link": "https://stackoverflow.com/users/690204/alonisser"
      },
      "is_answered": true,
      "view_count": 248185,
      "accepted_answer_id": 18801267,
      "answer_count": 14,
      "score": 369,
      "last_activity_date": 1681930989,
      "creation_date": 1379157185,
      "last_edit_date": 1495540968,
      "question_id": 18801147,
      "content_license": "CC BY-SA 3.0",
      "link": "https://stackoverflow.com/questions/18801147/changing-the-git-remote-push-to-default",
      "title": "Changing the Git remote &#39;push to&#39; default"
    },
    {
      "tags": [
        "sql",
        "postgresql",
        "postgresql-9.3"
      ],
      "owner": {
        "account_id": 183250,
        "reputation": 12408,
        "user_id": 418518,
        "user_type": "registered",
        "accept_rate": 75,
        "profile_image": "https://www.gravatar.com/avatar/773e2e200b4de16041095c00975d467c?s=256&d=identicon&r=PG",
        "display_name": "nothing-special-here",
        "link": "https://stackoverflow.com/users/418518/nothing-special-here"
      },
      "is_answered": true,
      "view_count": 412925,
      "accepted_answer_id": 21738505,
      "answer_count": 16,
      "score": 369,
      "last_activity_date": 1723835996,
      "creation_date": 1392235379,
      "last_edit_date": 1594431996,
      "question_id": 21738408,
      "content_license": "CC BY-SA 4.0",
      "link": "https://stackoverflow.com/questions/21738408/postgresql-list-and-order-tables-by-size",
      "title": "postgresql list and order tables by size"
    },
    {
      "tags": [
        "linux",
        "grep"
      ],
      "owner": {
        "account_id": 802229,
        "reputation": 4684,
        "user_id": 881846,
        "user_type": "registered",
        "accept_rate": 57,
        "profile_image": "https://i.sstatic.net/Plm5g.jpg?s=256",
        "display_name": "RandyTek",
        "link": "https://stackoverflow.com/users/881846/randytek"
      },
      "is_answered": true,
      "view_count": 183524,
      "closed_date": 1487261139,
      "accepted_answer_id": 25865916,
      "answer_count": 2,
      "score": 369,
      "last_activity_date": 1698927790,
      "creation_date": 1410802839,
      "last_edit_date": 1698927790,
      "question_id": 25853722,
      "link": "https://stackoverflow.com/questions/25853722/how-to-suppress-binary-file-matching-results-in-grep",
      "closed_reason": "Not suitable for this site",
      "title": "How to suppress binary file matching results in grep"
    },
    {
      "tags": [
        "inheritance",
        "kotlin",
        "abstract",
        "data-class"
      ],
      "owner": {
        "account_id": 1714632,
        "reputation": 4432,
        "user_id": 1625024,
        "user_type": "registered",
        "accept_rate": 60,
        "profile_image": "https://www.gravatar.com/avatar/feee7c8e957c35bb9fb72d24a91ae349?s=256&d=identicon&r=PG",
        "display_name": "Dmitry",
        "link": "https://stackoverflow.com/users/1625024/dmitry"
      },
      "is_answered": true,
      "view_count": 254313,
      "accepted_answer_id": 26467380,
      "answer_count": 15,
      "score": 369,
      "last_activity_date": 1710654511,
      "creation_date": 1413663518,
      "last_edit_date": 1578485597,
      "question_id": 26444145,
      "content_license": "CC BY-SA 4.0",
      "link": "https://stackoverflow.com/questions/26444145/extend-data-class-in-kotlin",
      "title": "Extend data class in Kotlin"
    },
    {
      "tags": [
        "pandas",
        "printing",
        "jupyter-notebook",
        "display"
      ],
      "owner": {
        "account_id": 4932712,
        "reputation": 13580,
        "user_id": 3971910,
        "user_type": "registered",
        "accept_rate": 87,
        "profile_image": "https://www.gravatar.com/avatar/4f4aaa1f047966c2202434cd2c352220?s=256&d=identicon&r=PG&f=y&so-version=2",
        "display_name": "Chris",
        "link": "https://stackoverflow.com/users/3971910/chris"
      },
      "is_answered": true,
      "view_count": 487643,
      "accepted_answer_id": 29665452,
      "answer_count": 9,
      "score": 369,
      "last_activity_date": 1663818011,
      "creation_date": 1415734853,
      "last_edit_date": 1479484124,
      "question_id": 26873127,
      "content_license": "CC BY-SA 3.0",
      "link": "https://stackoverflow.com/questions/26873127/show-dataframe-as-table-in-ipython-notebook",
      "title": "Show DataFrame as table in iPython Notebook"
    },
    {
      "tags": [
        "ios",
        "swift",
        "uitextfield"
      ],
      "owner": {
        "user_type": "does_not_exist",
        "display_name": "user4184036"
      },
      "is_answered": true,
      "view_count": 367148,
      "accepted_answer_id": 28395000,
      "answer_count": 21,
      "score": 369,
      "last_activity_date": 1683700166,
      "creation_date": 1423404984,
      "last_edit_date": 1474971398,
      "question_id": 28394933,
      "content_license": "CC BY-SA 3.0",
      "link": "https://stackoverflow.com/questions/28394933/how-do-i-check-when-a-uitextfield-changes",
      "title": "How do I check when a UITextField changes?"
    },
    {
      "tags": [
        "jupyter-notebook",
        "jupyter"
      ],
      "owner": {
        "account_id": 197844,
        "reputation": 6313,
        "user_id": 442158,
        "user_type": "registered",
        "accept_rate": 81,
        "profile_image": "https://www.gravatar.com/avatar/647f7f468d77030120927b6d47525c67?s=256&d=identicon&r=PG",
        "display_name": "chrisfs",
        "link": "https://stackoverflow.com/users/442158/chrisfs"
      },
      "is_answered": true,
      "view_count": 597874,
      "protected_date": 1529964546,
      "closed_date": 1538216311,
      "accepted_answer_id": 30981483,
      "answer_count": 18,
      "score": 369,
      "last_activity_date": 1610486769,
      "creation_date": 1430094957,
      "last_edit_date": 1610486769,
      "question_id": 29885371,
      "link": "https://stackoverflow.com/questions/29885371/how-do-i-block-comment-in-jupyter-notebook",
      "closed_reason": "Not suitable for this site",
      "title": "How do I block comment in Jupyter notebook?"
    },
    {
      "tags": [
        "php",
        "mysql",
        "laravel",
        "database"
      ],
      "owner": {
        "account_id": 1723114,
        "reputation": 7515,
        "user_id": 1578380,
        "user_type": "registered",
        "accept_rate": 36,
        "profile_image": "https://i.sstatic.net/53Pd1.jpg?s=256",
        "display_name": "Chintan7027",
        "link": "https://stackoverflow.com/users/1578380/chintan7027"
      },
      "is_answered": true,
      "view_count": 389899,
      "protected_date": 1501164755,
      "accepted_answer_id": 31847198,
      "answer_count": 11,
      "score": 369,
      "last_activity_date": 1729535648,
      "creation_date": 1438836475,
      "last_edit_date": 1640557916,
      "question_id": 31847054,
      "content_license": "CC BY-SA 4.0",
      "link": "https://stackoverflow.com/questions/31847054/how-to-use-multiple-databases-in-laravel",
      "title": "How to use multiple databases in Laravel"
    },
    {
      "tags": [
        "python",
        "amazon-web-services",
        "amazon-s3",
        "boto3"
      ],
      "owner": {
        "account_id": 1560620,
        "reputation": 6084,
        "user_id": 1474043,
        "user_type": "registered",
        "accept_rate": 44,
        "profile_image": "https://www.gravatar.com/avatar/aa077464b1c09ba73cbfeb1ffe98da58?s=256&d=identicon&r=PG",
        "display_name": "Prabhakar Shanmugam",
        "link": "https://stackoverflow.com/users/1474043/prabhakar-shanmugam"
      },
      "is_answered": true,
      "view_count": 402992,
      "accepted_answer_id": 33843019,
      "answer_count": 26,
      "score": 369,
      "last_activity_date": 1724231656,
      "creation_date": 1448106363,
      "last_edit_date": 1679001164,
      "question_id": 33842944,
      "content_license": "CC BY-SA 4.0",
      "link": "https://stackoverflow.com/questions/33842944/check-if-a-key-exists-in-a-bucket-in-s3-using-boto3",
      "title": "check if a key exists in a bucket in s3 using boto3"
    },
    {
      "tags": [
        "javascript",
        "ecmascript-6",
        "let"
      ],
      "owner": {
        "account_id": 2114516,
        "reputation": 14620,
        "user_id": 1879101,
        "user_type": "registered",
        "accept_rate": 88,
        "profile_image": "https://www.gravatar.com/avatar/baf034cf9d11e121dec031a98c312db4?s=256&d=identicon&r=PG",
        "display_name": "Vitaly Zdanevich",
        "link": "https://stackoverflow.com/users/1879101/vitaly-zdanevich"
      },
      "is_answered": true,
      "view_count": 146637,
      "accepted_answer_id": 37917071,
      "answer_count": 8,
      "score": 369,
      "last_activity_date": 1579724565,
      "creation_date": 1466408290,
      "last_edit_date": 1484020135,
      "question_id": 37916940,
      "content_license": "CC BY-SA 3.0",
      "link": "https://stackoverflow.com/questions/37916940/why-was-the-name-let-chosen-for-block-scoped-variable-declarations-in-javascri",
      "title": "Why was the name &#39;let&#39; chosen for block-scoped variable declarations in JavaScript?"
    },
    {
      "tags": [
        "git",
        "gnupg"
      ],
      "owner": {
        "account_id": 6769783,
        "reputation": 4911,
        "user_id": 5213477,
        "user_type": "registered",
        "accept_rate": 64,
        "profile_image": "https://i.sstatic.net/vI380.jpg?s=256",
        "display_name": "Entitize",
        "link": "https://stackoverflow.com/users/5213477/entitize"
      },
      "is_answered": true,
      "view_count": 234053,
      "protected_date": 1536176818,
      "accepted_answer_id": 41054093,
      "answer_count": 35,
      "score": 369,
      "last_activity_date": 1726730049,
      "creation_date": 1481253456,
      "last_edit_date": 1499837131,
      "question_id": 41052538,
      "content_license": "CC BY-SA 3.0",
      "link": "https://stackoverflow.com/questions/41052538/git-error-gpg-failed-to-sign-data",
      "title": "Git error - gpg failed to sign data"
    },
    {
      "tags": [
        "reactjs",
        "react-proptypes"
      ],
      "owner": {
        "account_id": 3370121,
        "reputation": 14368,
        "user_id": 2829540,
        "user_type": "registered",
        "accept_rate": 62,
        "profile_image": "https://i.sstatic.net/jCIIp.jpg?s=256",
        "display_name": "Kevin Amiranoff",
        "link": "https://stackoverflow.com/users/2829540/kevin-amiranoff"
      },
      "is_answered": true,
      "view_count": 177473,
      "accepted_answer_id": 41808543,
      "answer_count": 5,
      "score": 369,
      "last_activity_date": 1618383613,
      "creation_date": 1485181008,
      "last_edit_date": 1618383613,
      "question_id": 41808428,
      "content_license": "CC BY-SA 4.0",
      "link": "https://stackoverflow.com/questions/41808428/react-proptypes-allow-different-types-of-proptypes-for-one-prop",
      "title": "React PropTypes: Allow different types of PropTypes for one prop"
    },
    {
      "tags": [
        "flutter",
        "dart",
        "snackbar",
        "scaffold"
      ],
      "owner": {
        "account_id": 1577433,
        "reputation": 12509,
        "user_id": 1463542,
        "user_type": "registered",
        "accept_rate": 73,
        "profile_image": "https://www.gravatar.com/avatar/e1d24f8bf9532016baf8958a4ae39317?s=256&d=identicon&r=PG",
        "display_name": "Figen G&#252;ng&#246;r",
        "link": "https://stackoverflow.com/users/1463542/figen-g%c3%bcng%c3%b6r"
      },
      "is_answered": true,
      "view_count": 160560,
      "accepted_answer_id": 51304732,
      "answer_count": 16,
      "score": 369,
      "last_activity_date": 1685031326,
      "creation_date": 1531395130,
      "last_edit_date": 1640511224,
      "question_id": 51304568,
      "content_license": "CC BY-SA 4.0",
      "link": "https://stackoverflow.com/questions/51304568/scaffold-of-called-with-a-context-that-does-not-contain-a-scaffold",
      "title": "Scaffold.of() called with a context that does not contain a Scaffold"
    },
    {
      "tags": [
        "ios",
        "swift",
        "swiftui"
      ],
      "owner": {
        "account_id": 7172437,
        "reputation": 6020,
        "user_id": 5479510,
        "user_type": "registered",
        "profile_image": "https://i.sstatic.net/ii5Uy.jpg?s=256",
        "display_name": "inokey",
        "link": "https://stackoverflow.com/users/5479510/inokey"
      },
      "is_answered": true,
      "view_count": 376464,
      "accepted_answer_id": 56649668,
      "answer_count": 15,
      "score": 369,
      "last_activity_date": 1724164687,
      "creation_date": 1559649898,
      "last_edit_date": 1559731756,
      "question_id": 56443535,
      "content_license": "CC BY-SA 4.0",
      "link": "https://stackoverflow.com/questions/56443535/swiftui-text-alignment",
      "title": "SwiftUI text-alignment"
    },
    {
      "tags": [
        "javascript",
        "html",
        "debugging",
        "google-chrome-extension"
      ],
      "owner": {
        "account_id": 12977026,
        "reputation": 3984,
        "user_id": 11510013,
        "user_type": "registered",
        "profile_image": "https://lh5.googleusercontent.com/-oBTTQmrq_mA/AAAAAAAAAAI/AAAAAAAAANI/VTYhL_gyQXk/photo.jpg?sz=256",
        "display_name": "snehit vaddi",
        "link": "https://stackoverflow.com/users/11510013/snehit-vaddi"
      },
      "is_answered": true,
      "view_count": 1088729,
      "protected_date": 1609148609,
      "accepted_answer_id": 61442974,
      "answer_count": 22,
      "score": 369,
      "last_activity_date": 1698763923,
      "creation_date": 1587460595,
      "last_edit_date": 1681805806,
      "question_id": 61339968,
      "content_license": "CC BY-SA 4.0",
      "link": "https://stackoverflow.com/questions/61339968/error-message-devtools-failed-to-load-sourcemap-could-not-load-content-for-chr",
      "title": "Error message &quot;DevTools failed to load SourceMap: Could not load content for chrome-extension://...&quot;"
    },
    {
      "tags": [
        "emacs"
      ],
      "owner": {
        "account_id": 6588,
        "reputation": 37654,
        "user_id": 11138,
        "user_type": "registered",
        "accept_rate": 100,
        "profile_image": "https://www.gravatar.com/avatar/07b6238e229f4a9c9767893fd2e02b8b?s=256&d=identicon&r=PG",
        "display_name": "jfm3",
        "link": "https://stackoverflow.com/users/11138/jfm3"
      },
      "is_answered": true,
      "view_count": 138772,
      "accepted_answer_id": 151946,
      "answer_count": 7,
      "score": 368,
      "last_activity_date": 1696941402,
      "creation_date": 1222755308,
      "last_edit_date": 1222755879,
      "question_id": 151945,
      "content_license": "CC BY-SA 2.5",
      "link": "https://stackoverflow.com/questions/151945/how-do-i-control-how-emacs-makes-backup-files",
      "title": "How do I control how Emacs makes backup files?"
    },
    {
      "tags": [
        "ruby",
        "rubygems"
      ],
      "owner": {
        "account_id": 8248,
        "reputation": 76666,
        "user_id": 14755,
        "user_type": "registered",
        "accept_rate": 95,
        "profile_image": "https://www.gravatar.com/avatar/d6c40863eb4cc08dc0e41bef85a34407?s=256&d=identicon&r=PG",
        "display_name": "hectorsq",
        "link": "https://stackoverflow.com/users/14755/hectorsq"
      },
      "is_answered": true,
      "view_count": 386203,
      "accepted_answer_id": 220181,
      "answer_count": 9,
      "score": 368,
      "last_activity_date": 1572413526,
      "creation_date": 1224541937,
      "last_edit_date": 1379047918,
      "question_id": 220176,
      "content_license": "CC BY-SA 3.0",
      "link": "https://stackoverflow.com/questions/220176/how-can-i-install-a-local-gem",
      "title": "How can I install a local gem?"
    },
    {
      "tags": [
        "mysql",
        "database",
        "diff"
      ],
      "owner": {
        "account_id": 13598,
        "reputation": 103015,
        "user_id": 27439,
        "user_type": "registered",
        "accept_rate": 100,
        "profile_image": "https://i.sstatic.net/eMKDL.jpg?s=256",
        "display_name": "Vincent Ramdhanie",
        "link": "https://stackoverflow.com/users/27439/vincent-ramdhanie"
      },
      "is_answered": true,
      "view_count": 412956,
      "closed_date": 1341325847,
      "accepted_answer_id": 8718572,
      "answer_count": 21,
      "score": 368,
      "locked_date": 1447867535,
      "last_activity_date": 1523801101,
      "creation_date": 1224682867,
      "last_edit_date": 1523801101,
      "question_id": 225772,
      "link": "https://stackoverflow.com/questions/225772/compare-two-mysql-databases",
      "closed_reason": "not constructive",
      "title": "Compare two MySQL databases"
    },
    {
      "tags": [
        "unicode",
        "command-line",
        "input",
        "windows-console"
      ],
      "owner": {
        "account_id": 18162,
        "reputation": 106626,
        "user_id": 41360,
        "user_type": "registered",
        "accept_rate": 59,
        "profile_image": "https://i.sstatic.net/NXmaZ.png?s=256",
        "display_name": "Vilx-",
        "link": "https://stackoverflow.com/users/41360/vilx"
      },
      "is_answered": true,
      "view_count": 577091,
      "accepted_answer_id": 47843552,
      "answer_count": 19,
      "score": 368,
      "last_activity_date": 1692778039,
      "creation_date": 1230024659,
      "last_edit_date": 1684491426,
      "question_id": 388490,
      "content_license": "CC BY-SA 4.0",
      "link": "https://stackoverflow.com/questions/388490/how-can-i-use-unicode-characters-on-the-windows-command-line",
      "title": "How can I use Unicode characters on the Windows command line?"
    },
    {
      "tags": [
        "javascript",
        "html"
      ],
      "owner": {
        "account_id": 5559,
        "reputation": 544969,
        "user_id": 9021,
        "user_type": "registered",
        "accept_rate": 70,
        "profile_image": "https://www.gravatar.com/avatar/f092dfd45793e9483281d4205b674823?s=256&d=identicon&r=PG",
        "display_name": "nickf",
        "link": "https://stackoverflow.com/users/9021/nickf"
      },
      "is_answered": true,
      "view_count": 254159,
      "accepted_answer_id": 432201,
      "answer_count": 23,
      "score": 368,
      "last_activity_date": 1719213962,
      "creation_date": 1231639334,
      "last_edit_date": 1495542398,
      "question_id": 432174,
      "content_license": "CC BY-SA 3.0",
      "link": "https://stackoverflow.com/questions/432174/how-to-store-arbitrary-data-for-some-html-tags",
      "title": "How to store arbitrary data for some HTML tags"
    },
    {
      "tags": [
        "c++",
        "c",
        "refactoring",
        "include",
        "dependencies"
      ],
      "owner": {
        "account_id": 5846,
        "reputation": 78640,
        "user_id": 9611,
        "user_type": "registered",
        "accept_rate": 54,
        "profile_image": "https://www.gravatar.com/avatar/749b73007119baf94fc077c50bcc58e8?s=256&d=identicon&r=PG",
        "display_name": "shoosh",
        "link": "https://stackoverflow.com/users/9611/shoosh"
      },
      "is_answered": true,
      "view_count": 155232,
      "accepted_answer_id": 614925,
      "answer_count": 19,
      "score": 368,
      "last_activity_date": 1700673336,
      "creation_date": 1236260633,
      "last_edit_date": 1686683877,
      "question_id": 614794,
      "content_license": "CC BY-SA 4.0",
      "link": "https://stackoverflow.com/questions/614794/detecting-superfluous-includes-in-c-c",
      "title": "Detecting superfluous #includes in C/C++"
    },
    {
      "tags": [
        "c#",
        "entity-framework",
        "transactions"
      ],
      "owner": {
        "account_id": 31059,
        "reputation": 20877,
        "user_id": 85040,
        "user_type": "registered",
        "accept_rate": 79,
        "profile_image": "https://www.gravatar.com/avatar/990752653c19c5093055304680900a57?s=256&d=identicon&r=PG",
        "display_name": "mark smith",
        "link": "https://stackoverflow.com/users/85040/mark-smith"
      },
      "is_answered": true,
      "view_count": 310862,
      "accepted_answer_id": 815660,
      "answer_count": 4,
      "score": 368,
      "last_activity_date": 1662923626,
      "creation_date": 1241297403,
      "last_edit_date": 1490008814,
      "question_id": 815586,
      "content_license": "CC BY-SA 3.0",
      "link": "https://stackoverflow.com/questions/815586/using-transactions-or-savechangesfalse-and-acceptallchanges",
      "title": "Using Transactions or SaveChanges(false) and AcceptAllChanges()?"
    },
    {
      "tags": [
        "c++",
        "httprequest"
      ],
      "owner": {
        "account_id": 23742,
        "reputation": 19516,
        "user_id": 59730,
        "user_type": "registered",
        "accept_rate": 97,
        "profile_image": "https://www.gravatar.com/avatar/484049b7abb4431acc759da32055465a?s=256&d=identicon&r=PG&f=y&so-version=2",
        "display_name": "Sam Becker",
        "link": "https://stackoverflow.com/users/59730/sam-becker"
      },
      "is_answered": true,
      "view_count": 815818,
      "protected_date": 1705335275,
      "accepted_answer_id": 1112084,
      "answer_count": 25,
      "score": 368,
      "last_activity_date": 1705332283,
      "creation_date": 1245311561,
      "last_edit_date": 1420302453,
      "question_id": 1011339,
      "content_license": "CC BY-SA 3.0",
      "link": "https://stackoverflow.com/questions/1011339/how-do-you-make-a-http-request-with-c",
      "title": "How do you make a HTTP request with C++?"
    },
    {
      "tags": [
        "c++",
        "stdstring"
      ],
      "owner": {
        "account_id": 31720,
        "reputation": 6274,
        "user_id": 87349,
        "user_type": "registered",
        "accept_rate": 88,
        "profile_image": "https://www.gravatar.com/avatar/00f92cbdb3a1b02b19249c1e88d77b8e?s=256&d=identicon&r=PG",
        "display_name": "Jonathan Prior",
        "link": "https://stackoverflow.com/users/87349/jonathan-prior"
      },
      "is_answered": true,
      "view_count": 892729,
      "accepted_answer_id": 1195690,
      "answer_count": 13,
      "score": 368,
      "last_activity_date": 1697082742,
      "creation_date": 1248803734,
      "last_edit_date": 1522105073,
      "question_id": 1195675,
      "content_license": "CC BY-SA 3.0",
      "link": "https://stackoverflow.com/questions/1195675/convert-a-char-to-stdstring",
      "title": "convert a char* to std::string"
    },
    {
      "tags": [
        "floating-point",
        "comparison",
        "nan",
        "ieee-754",
        "iec10967"
      ],
      "owner": {
        "account_id": 20562,
        "reputation": 56546,
        "user_id": 49246,
        "user_type": "registered",
        "accept_rate": 73,
        "profile_image": "https://www.gravatar.com/avatar/c421b43470bb8d3c099c5a847e588549?s=256&d=identicon&r=PG",
        "display_name": "starblue",
        "link": "https://stackoverflow.com/users/49246/starblue"
      },
      "is_answered": true,
      "view_count": 78319,
      "protected_date": 1507028623,
      "accepted_answer_id": 1573715,
      "answer_count": 12,
      "score": 368,
      "last_activity_date": 1666120960,
      "creation_date": 1255511957,
      "last_edit_date": 1411143191,
      "question_id": 1565164,
      "content_license": "CC BY-SA 3.0",
      "link": "https://stackoverflow.com/questions/1565164/what-is-the-rationale-for-all-comparisons-returning-false-for-ieee754-nan-values",
      "title": "What is the rationale for all comparisons returning false for IEEE754 NaN values?"
    },
    {
      "tags": [
        "php",
        "tags",
        "php-shorttags"
      ],
      "owner": {
        "account_id": 74352,
        "reputation": 21905,
        "user_id": 213689,
        "user_type": "registered",
        "accept_rate": 87,
        "profile_image": "https://www.gravatar.com/avatar/65f0120102850ccf148ab0de3287ebb1?s=256&d=identicon&r=PG",
        "display_name": "seedg",
        "link": "https://stackoverflow.com/users/213689/seedg"
      },
      "is_answered": true,
      "view_count": 658859,
      "protected_date": 1408897359,
      "accepted_answer_id": 2185331,
      "answer_count": 21,
      "score": 368,
      "last_activity_date": 1621714848,
      "creation_date": 1265125450,
      "last_edit_date": 1368373305,
      "question_id": 2185320,
      "content_license": "CC BY-SA 3.0",
      "link": "https://stackoverflow.com/questions/2185320/how-to-enable-php-short-tags",
      "title": "How to enable PHP short tags?"
    },
    {
      "tags": [
        "python",
        "list",
        "merge",
        "tuples"
      ],
      "owner": {
        "account_id": 33625,
        "reputation": 9370,
        "user_id": 94250,
        "user_type": "registered",
        "accept_rate": 91,
        "profile_image": "https://www.gravatar.com/avatar/44060e16163fceaddae337f87357c6ca?s=256&d=identicon&r=PG",
        "display_name": "rubayeet",
        "link": "https://stackoverflow.com/users/94250/rubayeet"
      },
      "is_answered": true,
      "view_count": 376530,
      "protected_date": 1537820450,
      "accepted_answer_id": 2407405,
      "answer_count": 10,
      "score": 368,
      "last_activity_date": 1642229078,
      "creation_date": 1268121106,
      "last_edit_date": 1572789021,
      "question_id": 2407398,
      "content_license": "CC BY-SA 4.0",
      "link": "https://stackoverflow.com/questions/2407398/how-to-merge-lists-into-a-list-of-tuples",
      "title": "How to merge lists into a list of tuples?"
    },
    {
      "tags": [
        "java",
        "uuid"
      ],
      "owner": {
        "account_id": 12090,
        "reputation": 10428,
        "user_id": 23637,
        "user_type": "registered",
        "accept_rate": 83,
        "profile_image": "https://www.gravatar.com/avatar/5b55e7c59c71312dfaf37162915f6f4e?s=256&d=identicon&r=PG",
        "display_name": "Alvin",
        "link": "https://stackoverflow.com/users/23637/alvin"
      },
      "is_answered": true,
      "view_count": 220840,
      "protected_date": 1531751474,
      "answer_count": 9,
      "score": 368,
      "last_activity_date": 1563922791,
      "creation_date": 1269499917,
      "last_edit_date": 1560164304,
      "question_id": 2513573,
      "content_license": "CC BY-SA 4.0",
      "link": "https://stackoverflow.com/questions/2513573/how-good-is-javas-uuid-randomuuid",
      "title": "How good is Java&#39;s UUID.randomUUID?"
    },
    {
      "tags": [
        "javascript",
        "programming-languages"
      ],
      "owner": {
        "account_id": 13106,
        "reputation": 25354,
        "user_id": 26143,
        "user_type": "registered",
        "accept_rate": 61,
        "profile_image": "https://i.sstatic.net/9XaBm.jpg?s=256",
        "display_name": "gath",
        "link": "https://stackoverflow.com/users/26143/gath"
      },
      "is_answered": true,
      "view_count": 82207,
      "closed_date": 1322932097,
      "accepted_answer_id": 2629004,
      "answer_count": 29,
      "community_owned_date": 1276588894,
      "score": 368,
      "locked_date": 1333524904,
      "last_activity_date": 1315175537,
      "creation_date": 1271153601,
      "last_edit_date": 1271964035,
      "question_id": 2628672,
      "link": "https://stackoverflow.com/questions/2628672/what-should-every-javascript-programmer-know",
      "closed_reason": "not constructive",
      "title": "What should every JavaScript programmer know?"
    },
    {
      "tags": [
        "python"
      ],
      "owner": {
        "account_id": 77504,
        "reputation": 33980,
        "user_id": 221149,
        "user_type": "registered",
        "accept_rate": 75,
        "profile_image": "https://www.gravatar.com/avatar/b25e35d79f597348a0f24f2f816c34ce?s=256&d=identicon&r=PG",
        "display_name": "Hulk",
        "link": "https://stackoverflow.com/users/221149/hulk"
      },
      "is_answered": true,
      "view_count": 489678,
      "accepted_answer_id": 2872519,
      "answer_count": 23,
      "score": 368,
      "last_activity_date": 1715885706,
      "creation_date": 1274348223,
      "last_edit_date": 1468875799,
      "question_id": 2872512,
      "content_license": "CC BY-SA 3.0",
      "link": "https://stackoverflow.com/questions/2872512/python-truncate-a-long-string",
      "title": "Python truncate a long string"
    },
    {
      "tags": [
        "c++",
        "vector",
        "std",
        "stdvector"
      ],
      "owner": {
        "account_id": 55292,
        "reputation": 92616,
        "user_id": 165520,
        "user_type": "registered",
        "accept_rate": 80,
        "profile_image": "https://i.sstatic.net/yJCdp.jpg?s=256",
        "display_name": "Prasoon Saurav",
        "link": "https://stackoverflow.com/users/165520/prasoon-saurav"
      },
      "is_answered": true,
      "view_count": 637058,
      "accepted_answer_id": 3221813,
      "answer_count": 13,
      "score": 368,
      "last_activity_date": 1715325953,
      "creation_date": 1278820774,
      "last_edit_date": 1715325953,
      "question_id": 3221812,
      "content_license": "CC BY-SA 4.0",
      "link": "https://stackoverflow.com/questions/3221812/how-to-sum-up-elements-of-a-stdvector",
      "title": "How to sum up elements of a std::vector?"
    },
    {
      "tags": [
        "java",
        "intellij-idea",
        "metrics"
      ],
      "owner": {
        "account_id": 21585,
        "reputation": 6637,
        "user_id": 52563,
        "user_type": "registered",
        "accept_rate": 90,
        "profile_image": "https://www.gravatar.com/avatar/50f140266dc499bf8704c8799d6138a5?s=256&d=identicon&r=PG&f=y&so-version=2",
        "display_name": "Gary",
        "link": "https://stackoverflow.com/users/52563/gary"
      },
      "is_answered": true,
      "view_count": 235007,
      "accepted_answer_id": 4341885,
      "answer_count": 9,
      "score": 368,
      "last_activity_date": 1610150888,
      "creation_date": 1281293155,
      "last_edit_date": 1581509727,
      "question_id": 3435581,
      "content_license": "CC BY-SA 4.0",
      "link": "https://stackoverflow.com/questions/3435581/how-to-count-lines-of-java-code-using-intellij-idea",
      "title": "How to count lines of Java code using IntelliJ IDEA?"
    },
    {
      "tags": [
        "java",
        "design-patterns",
        "jsp",
        "servlets"
      ],
      "owner": {
        "account_id": 32599,
        "reputation": 9339,
        "user_id": 90575,
        "user_type": "registered",
        "accept_rate": 57,
        "profile_image": "https://www.gravatar.com/avatar/9e6570a26b531e084bce72172773dd9b?s=256&d=identicon&r=PG",
        "display_name": "mawia",
        "link": "https://stackoverflow.com/users/90575/mawia"
      },
      "is_answered": true,
      "view_count": 116765,
      "protected_date": 1517809711,
      "closed_date": 1517809723,
      "accepted_answer_id": 3542297,
      "answer_count": 5,
      "score": 368,
      "last_activity_date": 1517809663,
      "creation_date": 1282472422,
      "last_edit_date": 1509805766,
      "question_id": 3541077,
      "link": "https://stackoverflow.com/questions/3541077/design-patterns-web-based-applications",
      "closed_reason": "Opinion-based",
      "title": "Design Patterns web based applications"
    },
    {
      "tags": [
        "sqlite",
        "create-table",
        "database-table"
      ],
      "owner": {
        "account_id": 209837,
        "reputation": 4091,
        "user_id": 461112,
        "user_type": "registered",
        "accept_rate": 30,
        "profile_image": "https://www.gravatar.com/avatar/332d4c4a09f271a4a921ce52cbba0ae0?s=256&d=identicon&r=PG",
        "display_name": "user461112",
        "link": "https://stackoverflow.com/users/461112/user461112"
      },
      "is_answered": true,
      "view_count": 299065,
      "accepted_answer_id": 4098026,
      "answer_count": 2,
      "score": 368,
      "last_activity_date": 1692025711,
      "creation_date": 1288883055,
      "last_edit_date": 1446735216,
      "question_id": 4098008,
      "content_license": "CC BY-SA 3.0",
      "link": "https://stackoverflow.com/questions/4098008/create-table-in-sqlite-only-if-it-doesnt-exist-already",
      "title": "Create table in SQLite only if it doesn&#39;t exist already"
    },
    {
      "tags": [
        "php",
        "mysql"
      ],
      "owner": {
        "account_id": 109297,
        "reputation": 37247,
        "user_id": 289666,
        "user_type": "registered",
        "accept_rate": 78,
        "profile_image": "https://www.gravatar.com/avatar/7b73b931731be605e73692f0255d83e4?s=256&d=identicon&r=PG",
        "display_name": "Haroldo",
        "link": "https://stackoverflow.com/users/289666/haroldo"
      },
      "is_answered": true,
      "view_count": 743804,
      "protected_date": 1488571814,
      "accepted_answer_id": 4165253,
      "answer_count": 23,
      "score": 368,
      "last_activity_date": 1713360810,
      "creation_date": 1289569343,
      "question_id": 4165195,
      "content_license": "CC BY-SA 2.5",
      "link": "https://stackoverflow.com/questions/4165195/mysql-query-to-get-column-names",
      "title": "MySQL query to get column names?"
    },
    {
      "tags": [
        "javascript",
        "floating-point",
        "numbers",
        "decimal",
        "rounding"
      ],
      "owner": {
        "account_id": 687561,
        "reputation": 3691,
        "user_id": 549931,
        "user_type": "unregistered",
        "profile_image": "https://www.gravatar.com/avatar/4d1ebb8d2df447b78f4c593dd02e719f?s=256&d=identicon&r=PG",
        "display_name": "Oscar",
        "link": "https://stackoverflow.com/users/549931/oscar"
      },
      "is_answered": true,
      "view_count": 527988,
      "protected_date": 1522128673,
      "accepted_answer_id": 4512317,
      "answer_count": 32,
      "score": 368,
      "last_activity_date": 1693509290,
      "creation_date": 1293042008,
      "last_edit_date": 1608905600,
      "question_id": 4512306,
      "content_license": "CC BY-SA 4.0",
      "link": "https://stackoverflow.com/questions/4512306/get-decimal-portion-of-a-number-with-javascript",
      "title": "Get decimal portion of a number with JavaScript"
    },
    {
      "tags": [
        "android",
        "android-intent"
      ],
      "owner": {
        "account_id": 313448,
        "reputation": 8321,
        "user_id": 628090,
        "user_type": "registered",
        "accept_rate": 82,
        "profile_image": "https://www.gravatar.com/avatar/3dcd7084a35dd90be60bf0d55025ae67?s=256&d=identicon&r=PG",
        "display_name": "Shaista Naaz",
        "link": "https://stackoverflow.com/users/628090/shaista-naaz"
      },
      "is_answered": true,
      "view_count": 955321,
      "accepted_answer_id": 5265952,
      "answer_count": 18,
      "score": 368,
      "last_activity_date": 1704213896,
      "creation_date": 1299791202,
      "last_edit_date": 1539527856,
      "question_id": 5265913,
      "content_license": "CC BY-SA 4.0",
      "link": "https://stackoverflow.com/questions/5265913/how-to-use-putextra-and-getextra-for-string-data",
      "title": "How to use putExtra() and getExtra() for string data"
    },
    {
      "tags": [
        "bash",
        "function"
      ],
      "owner": {
        "account_id": 292005,
        "reputation": 16410,
        "user_id": 594496,
        "user_type": "registered",
        "accept_rate": 52,
        "profile_image": "https://www.gravatar.com/avatar/744c70118e658ebfd2da6ccc5c77c8d4?s=256&d=identicon&r=PG",
        "display_name": "k107",
        "link": "https://stackoverflow.com/users/594496/k107"
      },
      "is_answered": true,
      "view_count": 72318,
      "accepted_answer_id": 6916952,
      "answer_count": 4,
      "score": 368,
      "last_activity_date": 1543913578,
      "creation_date": 1312310107,
      "question_id": 6916856,
      "content_license": "CC BY-SA 3.0",
      "link": "https://stackoverflow.com/questions/6916856/can-bash-show-a-functions-definition",
      "title": "Can bash show a function&#39;s definition?"
    },
    {
      "tags": [
        "c#",
        "encoding",
        "base64"
      ],
      "owner": {
        "account_id": 793476,
        "reputation": 3691,
        "user_id": 904105,
        "user_type": "unregistered",
        "profile_image": "https://www.gravatar.com/avatar/06081398bce8b604ef5a8c36f23f67c2?s=256&d=identicon&r=PG",
        "display_name": "Rickard",
        "link": "https://stackoverflow.com/users/904105/rickard"
      },
      "is_answered": true,
      "view_count": 559969,
      "answer_count": 3,
      "score": 368,
      "last_activity_date": 1690922950,
      "creation_date": 1313876091,
      "last_edit_date": 1453448377,
      "question_id": 7134837,
      "content_license": "CC BY-SA 3.0",
      "link": "https://stackoverflow.com/questions/7134837/how-do-i-decode-a-base64-encoded-string",
      "title": "How do I decode a base64 encoded string?"
    },
    {
      "tags": [
        "java",
        "network-programming",
        "environment-variables",
        "hostname"
      ],
      "owner": {
        "account_id": 300025,
        "reputation": 3817,
        "user_id": 606945,
        "user_type": "registered",
        "accept_rate": 40,
        "profile_image": "https://www.gravatar.com/avatar/53aa3c0cf6b37d9c5953c9cb82e8ffc9?s=256&d=identicon&r=PG",
        "display_name": "Mahendra",
        "link": "https://stackoverflow.com/users/606945/mahendra"
      },
      "is_answered": true,
      "view_count": 467797,
      "answer_count": 13,
      "score": 368,
      "last_activity_date": 1705451720,
      "creation_date": 1315488037,
      "last_edit_date": 1466719618,
      "question_id": 7348711,
      "content_license": "CC BY-SA 3.0",
      "link": "https://stackoverflow.com/questions/7348711/recommended-way-to-get-hostname-in-java",
      "title": "Recommended way to get hostname in Java"
    },
    {
      "tags": [
        "javascript",
        "math",
        "decimal"
      ],
      "owner": {
        "account_id": 330389,
        "reputation": 18350,
        "user_id": 654480,
        "user_type": "registered",
        "accept_rate": 92,
        "profile_image": "https://www.gravatar.com/avatar/c271fb9642a3a6d7ea223661ce055669?s=256&d=identicon&r=PG",
        "display_name": "JacobTheDev",
        "link": "https://stackoverflow.com/users/654480/jacobthedev"
      },
      "is_answered": true,
      "view_count": 676915,
      "accepted_answer_id": 7641824,
      "answer_count": 14,
      "score": 368,
      "last_activity_date": 1690260951,
      "creation_date": 1317684477,
      "last_edit_date": 1684941311,
      "question_id": 7641818,
      "content_license": "CC BY-SA 4.0",
      "link": "https://stackoverflow.com/questions/7641818/how-can-i-remove-the-decimal-part-from-javascript-number",
      "title": "How can I remove the decimal part from JavaScript number?"
    },
    {
      "tags": [
        "scala"
      ],
      "owner": {
        "account_id": 298471,
        "reputation": 23008,
        "user_id": 604511,
        "user_type": "registered",
        "accept_rate": 72,
        "profile_image": "https://i.sstatic.net/GpbzW.jpg?s=256",
        "display_name": "Jesvin Jose",
        "link": "https://stackoverflow.com/users/604511/jesvin-jose"
      },
      "is_answered": true,
      "view_count": 158930,
      "accepted_answer_id": 9738862,
      "answer_count": 7,
      "score": 368,
      "last_activity_date": 1657175846,
      "creation_date": 1331901399,
      "question_id": 9737352,
      "content_license": "CC BY-SA 3.0",
      "link": "https://stackoverflow.com/questions/9737352/what-is-the-apply-function-in-scala",
      "title": "What is the apply function in Scala?"
    },
    {
      "tags": [
        "gradle"
      ],
      "owner": {
        "account_id": 1455866,
        "reputation": 3685,
        "user_id": 1371441,
        "user_type": "registered",
        "accept_rate": 25,
        "profile_image": "https://www.gravatar.com/avatar/0f8a12a19cb59fa5a4754d413d76c8a2?s=256&d=identicon&r=PG",
        "display_name": "manojpardeshi111",
        "link": "https://stackoverflow.com/users/1371441/manojpardeshi111"
      },
      "is_answered": true,
      "view_count": 299448,
      "accepted_answer_id": 10834567,
      "answer_count": 17,
      "score": 368,
      "last_activity_date": 1702429222,
      "creation_date": 1338469114,
      "last_edit_date": 1680769006,
      "question_id": 10834111,
      "content_license": "CC BY-SA 4.0",
      "link": "https://stackoverflow.com/questions/10834111/where-does-gradle-store-downloaded-jars-on-the-local-file-system",
      "title": "Where does Gradle store downloaded jars on the local file system"
    },
    {
      "tags": [
        "android",
        "android-dialogfragment"
      ],
      "owner": {
        "account_id": 250222,
        "reputation": 7575,
        "user_id": 526801,
        "user_type": "registered",
        "accept_rate": 78,
        "profile_image": "https://www.gravatar.com/avatar/88f8473f72c3dbc65ee3c21717898a6a?s=256&d=identicon&r=PG",
        "display_name": "AlejandroVK",
        "link": "https://stackoverflow.com/users/526801/alejandrovk"
      },
      "is_answered": true,
      "view_count": 85137,
      "accepted_answer_id": 15279400,
      "answer_count": 7,
      "score": 368,
      "last_activity_date": 1669204747,
      "creation_date": 1362676251,
      "last_edit_date": 1495541874,
      "question_id": 15277460,
      "content_license": "CC BY-SA 3.0",
      "link": "https://stackoverflow.com/questions/15277460/how-to-create-a-dialogfragment-without-title",
      "title": "How to create a DialogFragment without title?"
    },
    {
      "tags": [
        "android-studio",
        "ide"
      ],
      "owner": {
        "account_id": 1902139,
        "reputation": 6193,
        "user_id": 1717784,
        "user_type": "registered",
        "accept_rate": 83,
        "profile_image": "https://i.sstatic.net/zoWbp.png?s=256",
        "display_name": "mgibson",
        "link": "https://stackoverflow.com/users/1717784/mgibson"
      },
      "is_answered": true,
      "view_count": 223417,
      "protected_date": 1477324107,
      "accepted_answer_id": 26196451,
      "answer_count": 13,
      "score": 368,
      "last_activity_date": 1596373001,
      "creation_date": 1368896330,
      "last_edit_date": 1554909743,
      "question_id": 16626810,
      "content_license": "CC BY-SA 4.0",
      "link": "https://stackoverflow.com/questions/16626810/can-android-studio-be-used-to-run-standard-java-projects",
      "title": "Can Android Studio be used to run standard Java projects?"
    },
    {
      "tags": [
        "string",
        "path",
        "nio",
        "java-7"
      ],
      "owner": {
        "account_id": 2251953,
        "reputation": 13566,
        "user_id": 1983997,
        "user_type": "registered",
        "accept_rate": 78,
        "profile_image": "https://www.gravatar.com/avatar/a761be68bd7fee2d1b7a9cbbb31c3388?s=256&d=identicon&r=PG",
        "display_name": "mat_boy",
        "link": "https://stackoverflow.com/users/1983997/mat-boy"
      },
      "is_answered": true,
      "view_count": 411920,
      "accepted_answer_id": 16919543,
      "answer_count": 4,
      "score": 368,
      "last_activity_date": 1585096496,
      "creation_date": 1370353394,
      "question_id": 16919501,
      "content_license": "CC BY-SA 3.0",
      "link": "https://stackoverflow.com/questions/16919501/create-a-path-from-string-in-java7",
      "title": "Create a Path from String in Java7"
    },
    {
      "tags": [
        "android-studio",
        "logcat"
      ],
      "owner": {
        "account_id": 2924572,
        "reputation": 4029,
        "user_id": 2506173,
        "user_type": "registered",
        "accept_rate": 0,
        "profile_image": "https://www.gravatar.com/avatar/8317ce48594b08307064f7ab449c90fd?s=256&d=identicon&r=PG",
        "display_name": "user2506173",
        "link": "https://stackoverflow.com/users/2506173/user2506173"
      },
      "is_answered": true,
      "view_count": 335423,
      "protected_date": 1477346562,
      "answer_count": 69,
      "score": 368,
      "last_activity_date": 1688921584,
      "creation_date": 1372787276,
      "last_edit_date": 1551445489,
      "question_id": 17432358,
      "content_license": "CC BY-SA 4.0",
      "link": "https://stackoverflow.com/questions/17432358/android-studio-logcat-nothing-to-show",
      "title": "Android studio logcat nothing to show"
    },
    {
      "tags": [
        "ios",
        "iphone",
        "cocoa-touch",
        "interface-builder",
        "autolayout"
      ],
      "owner": {
        "account_id": 2107525,
        "reputation": 4367,
        "user_id": 1873508,
        "user_type": "registered",
        "accept_rate": 80,
        "profile_image": "https://www.gravatar.com/avatar/e85ce083f258c2ccfba1642e6a5253f3?s=256&d=identicon&r=PG",
        "display_name": "Guferos",
        "link": "https://stackoverflow.com/users/1873508/guferos"
      },
      "is_answered": true,
      "view_count": 214933,
      "protected_date": 1460979616,
      "accepted_answer_id": 18066138,
      "answer_count": 24,
      "score": 368,
      "last_activity_date": 1632106156,
      "creation_date": 1375730161,
      "last_edit_date": 1632106156,
      "question_id": 18065938,
      "content_license": "CC BY-SA 4.0",
      "link": "https://stackoverflow.com/questions/18065938/how-to-use-auto-layout-to-move-other-views-when-a-view-is-hidden",
      "title": "How to use Auto Layout to move other views when a view is hidden?"
    },
    {
      "tags": [
        "git",
        "git-tag"
      ],
      "owner": {
        "account_id": 1327442,
        "reputation": 112779,
        "user_id": 1420197,
        "user_type": "registered",
        "accept_rate": 95,
        "profile_image": "https://i.sstatic.net/h88Vk.jpg?s=256",
        "display_name": "Ionic\u0103 Biz\u0103u",
        "link": "https://stackoverflow.com/users/1420197/ionic%c4%83-biz%c4%83u"
      },
      "is_answered": true,
      "view_count": 131666,
      "accepted_answer_id": 19542426,
      "answer_count": 20,
      "score": 368,
      "last_activity_date": 1705317728,
      "creation_date": 1382532915,
      "last_edit_date": 1521049350,
      "question_id": 19542301,
      "content_license": "CC BY-SA 3.0",
      "link": "https://stackoverflow.com/questions/19542301/delete-all-tags-from-a-git-repository",
      "title": "Delete all tags from a Git repository"
    },
    {
      "tags": [
        "bash",
        "shell"
      ],
      "owner": {
        "account_id": 3390005,
        "reputation": 6296,
        "user_id": 2845038,
        "user_type": "registered",
        "accept_rate": 95,
        "profile_image": "https://i.sstatic.net/EzirQ.jpg?s=256",
        "display_name": "Victor Brunell",
        "link": "https://stackoverflow.com/users/2845038/victor-brunell"
      },
      "is_answered": true,
      "view_count": 590650,
      "accepted_answer_id": 20449556,
      "answer_count": 4,
      "score": 368,
      "last_activity_date": 1653780886,
      "creation_date": 1386473398,
      "last_edit_date": 1637970972,
      "question_id": 20449543,
      "content_license": "CC BY-SA 4.0",
      "link": "https://stackoverflow.com/questions/20449543/shell-equality-operators-eq",
      "title": "Shell equality operators (=, ==, -eq)"
    },
    {
      "tags": [
        "css",
        "layout",
        "flexbox"
      ],
      "owner": {
        "account_id": 56610,
        "reputation": 9246,
        "user_id": 169603,
        "user_type": "registered",
        "accept_rate": 70,
        "profile_image": "https://i.sstatic.net/wTbdc.jpg?s=256",
        "display_name": "Zilk",
        "link": "https://stackoverflow.com/users/169603/zilk"
      },
      "is_answered": true,
      "view_count": 439694,
      "accepted_answer_id": 25098486,
      "answer_count": 6,
      "score": 368,
      "last_activity_date": 1640905143,
      "creation_date": 1407003357,
      "last_edit_date": 1640905143,
      "question_id": 25098042,
      "content_license": "CC BY-SA 4.0",
      "link": "https://stackoverflow.com/questions/25098042/fill-remaining-vertical-space-with-css-using-displayflex",
      "title": "Fill remaining vertical space with CSS using display:flex"
    },
    {
      "tags": [
        "python",
        "arrays",
        "numpy",
        "multidimensional-array",
        "numpy-einsum"
      ],
      "owner": {
        "account_id": 4179074,
        "reputation": 4211,
        "user_id": 3424684,
        "user_type": "registered",
        "accept_rate": 32,
        "profile_image": "https://www.gravatar.com/avatar/1969a61c7c54613164a02217e97d588c?s=256&d=identicon&r=PG&f=y&so-version=2",
        "display_name": "Lance Strait",
        "link": "https://stackoverflow.com/users/3424684/lance-strait"
      },
      "is_answered": true,
      "view_count": 184881,
      "accepted_answer_id": 33641428,
      "answer_count": 8,
      "score": 368,
      "last_activity_date": 1659171072,
      "creation_date": 1411940031,
      "last_edit_date": 1659171072,
      "question_id": 26089893,
      "content_license": "CC BY-SA 4.0",
      "link": "https://stackoverflow.com/questions/26089893/understanding-numpys-einsum",
      "title": "Understanding NumPy&#39;s einsum"
    },
    {
      "tags": [
        "javascript",
        "html",
        "security",
        "http-headers",
        "content-security-policy"
      ],
      "owner": {
        "account_id": 1876666,
        "reputation": 18912,
        "user_id": 1697755,
        "user_type": "registered",
        "accept_rate": 66,
        "profile_image": "https://www.gravatar.com/avatar/a8c4150a496ed70ba7584f574d758453?s=256&d=identicon&r=PG",
        "display_name": "Schlaus",
        "link": "https://stackoverflow.com/users/1697755/schlaus"
      },
      "is_answered": true,
      "view_count": 403769,
      "protected_date": 1504802861,
      "accepted_answer_id": 30280371,
      "answer_count": 2,
      "score": 368,
      "last_activity_date": 1709371237,
      "creation_date": 1431807767,
      "last_edit_date": 1595273948,
      "question_id": 30280370,
      "content_license": "CC BY-SA 4.0",
      "link": "https://stackoverflow.com/questions/30280370/how-does-content-security-policy-csp-work",
      "title": "How does Content Security Policy (CSP) work?"
    },
    {
      "tags": [
        "angular",
        "dom-events",
        "event-propagation"
      ],
      "owner": {
        "account_id": 2273223,
        "reputation": 12127,
        "user_id": 2000124,
        "user_type": "registered",
        "accept_rate": 79,
        "profile_image": "https://i.sstatic.net/W8PnM.png?s=256",
        "display_name": "Roman Kolesnikov",
        "link": "https://stackoverflow.com/users/2000124/roman-kolesnikov"
      },
      "is_answered": true,
      "view_count": 391506,
      "accepted_answer_id": 41001184,
      "answer_count": 15,
      "score": 368,
      "last_activity_date": 1628512974,
      "creation_date": 1454947570,
      "last_edit_date": 1599910183,
      "question_id": 35274028,
      "content_license": "CC BY-SA 4.0",
      "link": "https://stackoverflow.com/questions/35274028/stop-mouse-event-propagation",
      "title": "Stop mouse event propagation"
    },
    {
      "tags": [
        "post",
        "postman",
        "httprequest"
      ],
      "owner": {
        "account_id": 4124789,
        "reputation": 3983,
        "user_id": 3384231,
        "user_type": "registered",
        "accept_rate": 62,
        "profile_image": "https://www.gravatar.com/avatar/1b94b52939095b4a9e28b9fc3d834cbf?s=256&d=identicon&r=PG&f=y&so-version=2",
        "display_name": "user3384231",
        "link": "https://stackoverflow.com/users/3384231/user3384231"
      },
      "is_answered": true,
      "view_count": 675533,
      "accepted_answer_id": 36183449,
      "answer_count": 16,
      "score": 368,
      "last_activity_date": 1708662949,
      "creation_date": 1458656801,
      "last_edit_date": 1589804984,
      "question_id": 36157105,
      "content_license": "CC BY-SA 4.0",
      "link": "https://stackoverflow.com/questions/36157105/postman-how-to-make-multiple-requests-at-the-same-time",
      "title": "Postman: How to make multiple requests at the same time"
    },
    {
      "tags": [
        "visual-studio-code"
      ],
      "owner": {
        "account_id": 3046411,
        "reputation": 7677,
        "user_id": 2581928,
        "user_type": "registered",
        "accept_rate": 71,
        "profile_image": "https://i.sstatic.net/c5iS3.png?s=256",
        "display_name": "RainingChain",
        "link": "https://stackoverflow.com/users/2581928/rainingchain"
      },
      "is_answered": true,
      "view_count": 265367,
      "protected_date": 1528074180,
      "accepted_answer_id": 40709472,
      "answer_count": 14,
      "score": 368,
      "last_activity_date": 1712160449,
      "creation_date": 1479675764,
      "last_edit_date": 1674228707,
      "question_id": 40709351,
      "content_license": "CC BY-SA 4.0",
      "link": "https://stackoverflow.com/questions/40709351/visual-studio-code-how-to-split-the-editor-vertically",
      "title": "Visual Studio Code: How to split the editor vertically"
    },
    {
      "tags": [
        "swift",
        "swift4"
      ],
      "owner": {
        "account_id": 136795,
        "reputation": 20040,
        "user_id": 340554,
        "user_type": "registered",
        "accept_rate": 93,
        "profile_image": "https://www.gravatar.com/avatar/91ca7460de809fd2d34d0b2458eec34d?s=256&d=identicon&r=PG&f=y&so-version=2",
        "display_name": "Adrian",
        "link": "https://stackoverflow.com/users/340554/adrian"
      },
      "is_answered": true,
      "view_count": 207814,
      "accepted_answer_id": 45562735,
      "answer_count": 21,
      "score": 368,
      "last_activity_date": 1669384344,
      "creation_date": 1502179467,
      "last_edit_date": 1592873788,
      "question_id": 45562662,
      "content_license": "CC BY-SA 4.0",
      "link": "https://stackoverflow.com/questions/45562662/how-can-i-use-string-substring-in-swift-4-substringto-is-deprecated-pleas",
      "title": "How can I use String substring in Swift 4? &#39;substring(to:)&#39; is deprecated: Please use String slicing subscript with a &#39;partial range from&#39; operator"
    },
    {
      "tags": [
        "angular",
        "angular-webpack-starter"
      ],
      "owner": {
        "account_id": 4271232,
        "reputation": 5986,
        "user_id": 3492996,
        "user_type": "registered",
        "accept_rate": 50,
        "profile_image": "https://www.gravatar.com/avatar/e202fdc904bc94cfaeee826c6690dcd5?s=256&d=identicon&r=PG&f=y&so-version=2",
        "display_name": "mrapi",
        "link": "https://stackoverflow.com/users/3492996/mrapi"
      },
      "is_answered": true,
      "view_count": 435826,
      "accepted_answer_id": 46990483,
      "answer_count": 25,
      "score": 368,
      "last_activity_date": 1612525134,
      "creation_date": 1509198188,
      "last_edit_date": 1555428940,
      "question_id": 46990389,
      "content_license": "CC BY-SA 4.0",
      "link": "https://stackoverflow.com/questions/46990389/angular-4-no-component-factory-found-did-you-add-it-to-ngmodule-entrycomponent",
      "title": "Angular 4: no component factory found,did you add it to @NgModule.entryComponents?"
    },
    {
      "tags": [
        "python",
        "neural-network",
        "deep-learning",
        "pytorch",
        "gradient-descent"
      ],
      "owner": {
        "account_id": 1526413,
        "reputation": 13389,
        "user_id": 1424739,
        "user_type": "registered",
        "accept_rate": 17,
        "profile_image": "https://www.gravatar.com/avatar/19d3c927744b5ad3b94afbf88e1c3844?s=256&d=identicon&r=PG",
        "display_name": "user1424739",
        "link": "https://stackoverflow.com/users/1424739/user1424739"
      },
      "is_answered": true,
      "view_count": 297025,
      "accepted_answer_id": 48009142,
      "answer_count": 8,
      "score": 368,
      "last_activity_date": 1707413515,
      "creation_date": 1514435500,
      "last_edit_date": 1648471698,
      "question_id": 48001598,
      "content_license": "CC BY-SA 4.0",
      "link": "https://stackoverflow.com/questions/48001598/why-do-we-need-to-call-zero-grad-in-pytorch",
      "title": "Why do we need to call zero_grad() in PyTorch?"
    },
    {
      "tags": [
        "bash",
        "ssh",
        "csh"
      ],
      "owner": {
        "account_id": 140,
        "reputation": 5765,
        "user_id": 171,
        "user_type": "registered",
        "accept_rate": 71,
        "profile_image": "https://www.gravatar.com/avatar/b14d83ceb029c44f8487fee4ea3b8241?s=256&d=identicon&r=PG",
        "display_name": "dagorym",
        "link": "https://stackoverflow.com/users/171/dagorym"
      },
      "is_answered": true,
      "view_count": 401545,
      "accepted_answer_id": 29172,
      "answer_count": 19,
      "score": 367,
      "last_activity_date": 1681244647,
      "creation_date": 1219791358,
      "last_edit_date": 1598479053,
      "question_id": 29142,
      "content_license": "CC BY-SA 4.0",
      "link": "https://stackoverflow.com/questions/29142/getting-ssh-to-execute-a-command-in-the-background-on-target-machine",
      "title": "Getting ssh to execute a command in the background on target machine"
    },
    {
      "tags": [
        "c++",
        "operators",
        "language-design",
        "comparison-operators",
        "default-comparisons"
      ],
      "owner": {
        "account_id": 5660,
        "reputation": 78308,
        "user_id": 9236,
        "user_type": "registered",
        "accept_rate": 94,
        "profile_image": "https://www.gravatar.com/avatar/5d6db59f028e16f93d3af876c0e73129?s=256&d=identicon&r=PG",
        "display_name": "Rob",
        "link": "https://stackoverflow.com/users/9236/rob"
      },
      "is_answered": true,
      "view_count": 120217,
      "accepted_answer_id": 217934,
      "answer_count": 13,
      "score": 367,
      "last_activity_date": 1703084906,
      "creation_date": 1224495756,
      "last_edit_date": 1703084906,
      "question_id": 217911,
      "content_license": "CC BY-SA 4.0",
      "link": "https://stackoverflow.com/questions/217911/why-dont-c-compilers-define-operator-and-operator",
      "title": "Why don&#39;t C++ compilers define operator== and operator!=?"
    },
    {
      "tags": [
        "mysql",
        "logging"
      ],
      "owner": {
        "account_id": 1032,
        "reputation": 12940,
        "user_id": 1368,
        "user_type": "registered",
        "accept_rate": 41,
        "profile_image": "https://i.sstatic.net/nxfH8.jpg?s=256",
        "display_name": "public static",
        "link": "https://stackoverflow.com/users/1368/public-static"
      },
      "is_answered": true,
      "view_count": 480404,
      "protected_date": 1414785920,
      "accepted_answer_id": 304008,
      "answer_count": 8,
      "score": 367,
      "last_activity_date": 1666101657,
      "creation_date": 1227141541,
      "question_id": 303994,
      "content_license": "CC BY-SA 2.5",
      "link": "https://stackoverflow.com/questions/303994/log-all-queries-in-mysql",
      "title": "Log all queries in mysql"
    },
    {
      "tags": [
        "c#",
        ".net",
        "wpf",
        "image"
      ],
      "owner": {
        "account_id": 11671,
        "reputation": 6473,
        "user_id": 22621,
        "user_type": "registered",
        "accept_rate": 67,
        "profile_image": "https://www.gravatar.com/avatar/8bc7bb10bee96efb190053fe92ffd250?s=256&d=identicon&r=PG",
        "display_name": "Torbj&#248;rn",
        "link": "https://stackoverflow.com/users/22621/torbj%c3%b8rn"
      },
      "is_answered": true,
      "view_count": 649938,
      "accepted_answer_id": 1651397,
      "answer_count": 19,
      "score": 367,
      "last_activity_date": 1624903183,
      "creation_date": 1228752929,
      "last_edit_date": 1547190193,
      "question_id": 350027,
      "content_license": "CC BY-SA 4.0",
      "link": "https://stackoverflow.com/questions/350027/setting-wpf-image-source-in-code",
      "title": "Setting WPF image source in code"
    },
    {
      "tags": [
        "python",
        "video",
        "wxpython",
        "animated-gif"
      ],
      "owner": {
        "account_id": 32514,
        "reputation": 76394,
        "user_id": 90308,
        "user_type": "registered",
        "accept_rate": 93,
        "profile_image": "https://www.gravatar.com/avatar/7b7aefbc459629eb4c864b825894c9c4?s=256&d=identicon&r=PG",
        "display_name": "FogleBird",
        "link": "https://stackoverflow.com/users/90308/foglebird"
      },
      "is_answered": true,
      "view_count": 486012,
      "protected_date": 1617549527,
      "accepted_answer_id": 753832,
      "answer_count": 24,
      "score": 367,
      "last_activity_date": 1674306186,
      "creation_date": 1239821834,
      "last_edit_date": 1239825581,
      "question_id": 753190,
      "content_license": "CC BY-SA 2.5",
      "link": "https://stackoverflow.com/questions/753190/programmatically-generate-video-or-animated-gif-in-python",
      "title": "Programmatically generate video or animated GIF in Python?"
    },
    {
      "tags": [
        "c#",
        ".net",
        "events",
        "event-handling"
      ],
      "owner": {
        "account_id": 29725,
        "reputation": 6075,
        "user_id": 80535,
        "user_type": "registered",
        "accept_rate": 95,
        "profile_image": "https://lh5.googleusercontent.com/-4k5qq9mCyDY/AAAAAAAAAAI/AAAAAAAABpo/PQk643ckE-Y/photo.jpg?sz=256",
        "display_name": "Levi Campbell",
        "link": "https://stackoverflow.com/users/80535/levi-campbell"
      },
      "is_answered": true,
      "view_count": 451435,
      "accepted_answer_id": 803320,
      "answer_count": 13,
      "score": 367,
      "last_activity_date": 1634377841,
      "creation_date": 1241023283,
      "last_edit_date": 1343602747,
      "question_id": 803242,
      "content_license": "CC BY-SA 3.0",
      "link": "https://stackoverflow.com/questions/803242/understanding-events-and-event-handlers-in-c",
      "title": "Understanding events and event handlers in C#"
    },
    {
      "tags": [
        "javascript",
        "debugging",
        "console"
      ],
      "owner": {
        "account_id": 36610,
        "reputation": 8415,
        "user_id": 104461,
        "user_type": "registered",
        "accept_rate": 87,
        "profile_image": "https://i.sstatic.net/Yca56.png?s=256",
        "display_name": "Zack Burt",
        "link": "https://stackoverflow.com/users/104461/zack-burt"
      },
      "is_answered": true,
      "view_count": 371478,
      "accepted_answer_id": 1215400,
      "answer_count": 41,
      "score": 367,
      "last_activity_date": 1724167870,
      "creation_date": 1249084231,
      "last_edit_date": 1488269771,
      "question_id": 1215392,
      "content_license": "CC BY-SA 3.0",
      "link": "https://stackoverflow.com/questions/1215392/how-to-quickly-and-conveniently-disable-all-console-log-statements-in-my-code",
      "title": "How to quickly and conveniently disable all console.log statements in my code?"
    },
    {
      "tags": [
        "sql",
        "sql-server",
        "t-sql",
        "ado.net",
        "concurrency"
      ],
      "owner": {
        "account_id": 13638,
        "reputation": 431042,
        "user_id": 27535,
        "user_type": "registered",
        "accept_rate": 89,
        "profile_image": "https://www.gravatar.com/avatar/4190f05bc2af559580aa220d0139e9f8?s=256&d=identicon&r=PG",
        "display_name": "gbn",
        "link": "https://stackoverflow.com/users/27535/gbn"
      },
      "is_answered": true,
      "view_count": 322784,
      "accepted_answer_id": 1547539,
      "answer_count": 17,
      "community_owned_date": 1370592427,
      "score": 367,
      "last_activity_date": 1715671867,
      "creation_date": 1254063149,
      "last_edit_date": 1495540046,
      "question_id": 1483732,
      "content_license": "CC BY-SA 3.0",
      "link": "https://stackoverflow.com/questions/1483732/set-nocount-on-usage",
      "title": "SET NOCOUNT ON usage"
    },
    {
      "tags": [
        "python",
        "django",
        "datetime",
        "django-models",
        "django-admin"
      ],
      "owner": {
        "account_id": 32427,
        "reputation": 50412,
        "user_id": 90025,
        "user_type": "registered",
        "accept_rate": 85,
        "profile_image": "https://www.gravatar.com/avatar/b3bb70a4bace7f9bd49f48b149ab95f9?s=256&d=identicon&r=PG",
        "display_name": "Paul Tarjan",
        "link": "https://stackoverflow.com/users/90025/paul-tarjan"
      },
      "is_answered": true,
      "view_count": 431387,
      "accepted_answer_id": 1737078,
      "answer_count": 15,
      "score": 367,
      "last_activity_date": 1711550532,
      "creation_date": 1258274876,
      "last_edit_date": 1412132474,
      "question_id": 1737017,
      "content_license": "CC BY-SA 3.0",
      "link": "https://stackoverflow.com/questions/1737017/django-auto-now-and-auto-now-add",
      "title": "Django auto_now and auto_now_add"
    },
    {
      "tags": [
        "objective-c",
        "cocoa-touch",
        "first-responder"
      ],
      "owner": {
        "account_id": 49729,
        "reputation": 8414,
        "user_id": 148208,
        "user_type": "registered",
        "accept_rate": 74,
        "profile_image": "https://www.gravatar.com/avatar/aa0490fa29da8a5d40dd219d9f13dccb?s=256&d=identicon&r=PG",
        "display_name": "Justin Kredible",
        "link": "https://stackoverflow.com/users/148208/justin-kredible"
      },
      "is_answered": true,
      "view_count": 181172,
      "accepted_answer_id": 1823360,
      "answer_count": 26,
      "score": 367,
      "last_activity_date": 1648693092,
      "creation_date": 1259627474,
      "last_edit_date": 1389565617,
      "question_id": 1823317,
      "content_license": "CC BY-SA 3.0",
      "link": "https://stackoverflow.com/questions/1823317/get-the-current-first-responder-without-using-a-private-api",
      "title": "Get the current first responder without using a private API"
    },
    {
      "tags": [
        "python",
        "windows",
        "csv",
        "newline"
      ],
      "owner": {
        "account_id": 43684,
        "reputation": 5173,
        "user_id": 127819,
        "user_type": "registered",
        "accept_rate": 86,
        "profile_image": "https://www.gravatar.com/avatar/8794e02928ccc1cf06576226989d43d9?s=256&d=identicon&r=PG",
        "display_name": "apalopohapa",
        "link": "https://stackoverflow.com/users/127819/apalopohapa"
      },
      "is_answered": true,
      "view_count": 329849,
      "accepted_answer_id": 3191811,
      "answer_count": 6,
      "score": 367,
      "last_activity_date": 1615640583,
      "creation_date": 1278470065,
      "last_edit_date": 1615640583,
      "question_id": 3191528,
      "content_license": "CC BY-SA 4.0",
      "link": "https://stackoverflow.com/questions/3191528/csv-in-python-adding-an-extra-carriage-return-on-windows",
      "title": "CSV in Python adding an extra carriage return, on Windows"
    },
    {
      "tags": [
        "javascript",
        "callback",
        "parameter-passing"
      ],
      "owner": {
        "account_id": 62628,
        "reputation": 19396,
        "user_id": 185921,
        "user_type": "registered",
        "accept_rate": 73,
        "profile_image": "https://i.sstatic.net/wVINJ.png?s=256",
        "display_name": "vitto",
        "link": "https://stackoverflow.com/users/185921/vitto"
      },
      "is_answered": true,
      "view_count": 613581,
      "accepted_answer_id": 3458612,
      "answer_count": 17,
      "score": 367,
      "last_activity_date": 1729746846,
      "creation_date": 1281531949,
      "last_edit_date": 1729746846,
      "question_id": 3458553,
      "content_license": "CC BY-SA 4.0",
      "link": "https://stackoverflow.com/questions/3458553/javascript-passing-parameters-to-a-callback-function",
      "title": "JavaScript: Passing parameters to a callback function"
    },
    {
      "tags": [
        "sql-server",
        "datetime"
      ],
      "owner": {
        "account_id": 152275,
        "reputation": 4143,
        "user_id": 366685,
        "user_type": "registered",
        "accept_rate": 90,
        "profile_image": "https://www.gravatar.com/avatar/058822c36faf5557ded846086ec58ee6?s=256&d=identicon&r=PG",
        "display_name": "stephmoreland",
        "link": "https://stackoverflow.com/users/366685/stephmoreland"
      },
      "is_answered": true,
      "view_count": 1130185,
      "protected_date": 1553132567,
      "accepted_answer_id": 4888388,
      "answer_count": 12,
      "score": 367,
      "last_activity_date": 1598959809,
      "creation_date": 1296748059,
      "last_edit_date": 1513695012,
      "question_id": 4888277,
      "content_license": "CC BY-SA 3.0",
      "link": "https://stackoverflow.com/questions/4888277/add-default-value-of-datetime-field-in-sql-server-to-a-timestamp",
      "title": "Add default value of datetime field in SQL Server to a timestamp"
    }
  ],
  "has_more": true,
  "quota_max": 10000,
  "quota_remaining": 9828
}